pelican/themes/themeless/templates/archives.html
pelican/themes/themeless/templates/article.html
pelican/themes/themeless/templates/author.html
pelican/themes/themeless/templates/authors.html
pelican/themes/themeless/templates/categories.html
pelican/themes/themeless/templates/category.html
pelican/themes/themeless/templates/drafts.html
pelican/themes/themeless/templates/index.html
pelican/themes/themeless/templates/page.html
pelican/themes/themeless/templates/pages.html
pelican/themes/themeless/templates/period_archives.html
pelican/themes/themeless/templates/tag.html
pelican/themes/themeless/templates/tags.html
pelican/themes/themeless/templates/include/article.html
pelican/themes/themeless/templates/include/article_list_page.html
pelican/themes/themeless/templates/include/article_page.html
pelican/themes/themeless/templates/include/article_summary.html
pelican/themes/themeless/templates/include/base.html
pelican/themes/themeless/templates/include/paginator.html
pelican/themes/themeless/templates/include/property_list_page.html
pelican_themeless/__init__.py
pelican_themeless-0.1.2.dist-info/LICENSE.txt
pelican_themeless-0.1.2.dist-info/METADATA
pelican_themeless-0.1.2.dist-info/WHEEL
pelican_themeless-0.1.2.dist-info/top_level.txt
pelican_themeless-0.1.2.dist-info/RECORD
